vdb/__init__.py
vdb/debug_computation.py
vdb/eth_tester_debug_backend.py
vdb/source_map.py
vdb/variables.py
vdb/vdb.py
vyper_debug-0.1.2b7.data/scripts/vyper-run
vyper_debug-0.1.2b7.dist-info/LICENSE
vyper_debug-0.1.2b7.dist-info/METADATA
vyper_debug-0.1.2b7.dist-info/WHEEL
vyper_debug-0.1.2b7.dist-info/top_level.txt
vyper_debug-0.1.2b7.dist-info/RECORD
